libclipper.so
lanms_adaptor.cpython-36m-x86_64-linux-gnu.so
lanms/__init__.py
lanms_proper-1.0.1.dist-info/RECORD
lanms_proper-1.0.1.dist-info/top_level.txt
lanms_proper-1.0.1.dist-info/METADATA
lanms_proper-1.0.1.dist-info/WHEEL
.libslanms_adaptor/libclipper-1079f5fb.so
