Metadata-Version: 2.1
Name: lanms-proper
Version: 1.0.1
Summary: UNKNOWN
Home-page: UNKNOWN
Author: Some Guy
Author-email: idk@whatever.xyz
License: UNKNOWN
Platform: UNKNOWN
Requires-Dist: numpy
